fbpageplc/__init__.py
fbpageplc-0.6.dist-info/DESCRIPTION.rst
fbpageplc-0.6.dist-info/METADATA
fbpageplc-0.6.dist-info/RECORD
fbpageplc-0.6.dist-info/WHEEL
fbpageplc-0.6.dist-info/metadata.json
fbpageplc-0.6.dist-info/top_level.txt
