Metadata-Version: 2.0
Name: fbpageplc
Version: 0.6
Summary: Fetch posts, likes, comments of a public facebook page.
Home-page: https://github.com/akash0824/fbpageplc
Author: akash0824
Author-email: akashkumar0824@gmail.com
License: UNKNOWN
Platform: UNKNOWN
